{
  "node": {
    "status": {
      "locked": false,
      "agent_version": null,
      "operational": 2,
      "trust_details": {
        "bios": 0,
        "vmm": 0
      },
      "long_message": "Compute service is enabled. Compute service is working. No Agent installed!",
      "health": 2,
      "mode": 0,
      "trust": 0,
      "short_message": "Compute service is enabled."
    },
    "ids": {
      "platform_id": null,
      "mac": null,
      "ip_address": null,
      "cloud_id": null
    },
    "scheduler_persistent": false,
    "links": {
      "uri": "/api/v1/nodes/B2D1C20A-CA94-E111-BD1D-001E6747F5BA",
      "logs": "/api/v1/logs?node=B2D1C20A-CA94-E111-BD1D-001E6747F5BA"
    },
    "utilization": {
      "ipc": null,
      "uptime": null,
      "network": null,
      "cpu_frequency_current": null,
      "gips_max": null,
      "io": null,
      "memory": null,
      "gips_current": null,
      "cpu": {
        "iowait": null,
        "idle": null,
        "total": null,
        "steal": null,
        "guest": null
      }
    },
    "graphite_url": null,
    "sam_registered": false,
    "uri": "/nodes/B2D1C20A-CA94-E111-BD1D-001E6747F5BA",
    "capabilities": {
      "hyperthreading": null,
      "cores_per_socket": null,
      "cpu_frequency": null,
      "turbo_mode": null,
      "memory_size": null,
      "cpu_type": null,
      "cache_size": null,
      "sockets": null
    },
    "node_name": "novamgmt86",
    "sam_controlled": 0,
    "vcpus": {
      "max": 512,
      "used": 0
    },
    "scheduler_mark": null,
    "vm_info": {
      "count": 0,
      "max": null
    },
    "memory": {
      "max": 7887,
      "used": 512
    },
    "tier": null,
    "id": "B2D1C20A-CA94-E111-BD1D-001E6747F5BA",
    "vm_ids": [],
    "contention": {
      "sockets": null,
      "system": {
        "llc": {
          "value": null,
          "label": null
        }
      }
    }
  }
}